UnBIAS/__init__.py
UnBIAS/unbias.py
UnBIAS-3.0.2.dist-info/License.txt
UnBIAS-3.0.2.dist-info/METADATA
UnBIAS-3.0.2.dist-info/WHEEL
UnBIAS-3.0.2.dist-info/top_level.txt
UnBIAS-3.0.2.dist-info/RECORD
