Metadata-Version: 2.1
Name: UnBIAS
Version: 3.0.2
Summary: A package based on LLMs for detecting bias, performing named entity, and debiasing text.
Home-page: https://unbias-mkdocs.readthedocs.io/en/latest/
Author: Shaina Raza
Author-email: shaina.raza@utoronto.ca
Classifier: Programming Language :: Python :: 3
Classifier: License :: OSI Approved :: MIT License
Classifier: Operating System :: OS Independent
License-File: License.txt
Requires-Dist: transformers ==4.31.0
Requires-Dist: bitsandbytes ==0.40.2
Requires-Dist: accelerate ==0.21.0
Requires-Dist: pandas
Requires-Dist: torch
Requires-Dist: peft
Requires-Dist: trl
Requires-Dist: fire
Requires-Dist: datasets
Requires-Dist: sentencepiece
